media_crawler/__init__.py
media_crawler/config.py
media_crawler/crawler.py
media_crawler/database.py
media_crawler/downloader.py
media_crawler/exceptions.py
media_crawler/factory.py
media_crawler/link_extractor.py
media_crawler/progress.py
media_crawler/state_manager.py
media_crawler/utils.py
media_crawler/webdriver.py
pymedia_crawler-1.0.3.dist-info/licenses/LICENSE
pymedia_crawler-1.0.3.dist-info/METADATA
pymedia_crawler-1.0.3.dist-info/WHEEL
pymedia_crawler-1.0.3.dist-info/entry_points.txt
pymedia_crawler-1.0.3.dist-info/top_level.txt
pymedia_crawler-1.0.3.dist-info/RECORD
