Metadata-Version: 2.4
Name: pymedia-crawler
Version: 1.0.3
Summary: A robust, extensible web crawler for downloading media content
Home-page: https://github.com/hasanragab/media-crawler
Author: Hasan Ragab
Author-email: Hasan Ragab <hasanmragab@gmail.com>
License: MIT
Project-URL: Homepage, https://github.com/HasanRagab/media-crawler
Project-URL: Documentation, https://github.com/HasanRagab/media-crawler/docs
Project-URL: Repository, https://github.com/HasanRagab/media-crawler
Project-URL: Issues, https://github.com/HasanRagab/media-crawler/issues
Classifier: Development Status :: 4 - Beta
Classifier: Intended Audience :: Developers
Classifier: Topic :: Software Development :: Libraries :: Python Modules
Classifier: Topic :: Internet :: WWW/HTTP :: Dynamic Content
Classifier: Topic :: Multimedia :: Sound/Audio :: Capture/Recording
Classifier: Programming Language :: Python :: 3
Classifier: Programming Language :: Python :: 3.8
Classifier: Programming Language :: Python :: 3.9
Classifier: Programming Language :: Python :: 3.10
Classifier: Programming Language :: Python :: 3.11
Classifier: Programming Language :: Python :: 3.12
Classifier: License :: OSI Approved :: MIT License
Classifier: Operating System :: OS Independent
Requires-Python: >=3.8
License-File: LICENSE
Requires-Dist: selenium>=4.0.0
Requires-Dist: beautifulsoup4>=4.11.0
Requires-Dist: yt-dlp>=2023.0.0
Requires-Dist: urllib3>=1.26.0
Provides-Extra: dev
Requires-Dist: pytest>=7.0.0; extra == "dev"
Requires-Dist: pytest-cov>=4.0.0; extra == "dev"
Requires-Dist: black>=23.0.0; extra == "dev"
Requires-Dist: flake8>=6.0.0; extra == "dev"
Requires-Dist: mypy>=1.0.3; extra == "dev"
Provides-Extra: auto-chromedriver
Requires-Dist: webdriver-manager>=4.0.0; extra == "auto-chromedriver"
Dynamic: author
Dynamic: home-page
Dynamic: license-file
Dynamic: requires-python
